django_alive/__init__.py
django_alive/checks.py
django_alive/middleware.py
django_alive/urls.py
django_alive/utils.py
django_alive/views.py
django_alive/management/__init__.py
django_alive/management/commands/__init__.py
django_alive/management/commands/healthcheck.py
django_alive/tests/__init__.py
django_alive/tests/settings.py
django_alive/tests/side_effects.py
django_alive/tests/test_checks.py
django_alive/tests/test_command.py
django_alive/tests/test_middleware.py
django_alive/tests/test_views.py
django_alive-2.0.0.dist-info/LICENSE
django_alive-2.0.0.dist-info/METADATA
django_alive-2.0.0.dist-info/WHEEL
django_alive-2.0.0.dist-info/top_level.txt
django_alive-2.0.0.dist-info/RECORD
