Metadata-Version: 2.1
Name: django-alive
Version: 2.0.0
Summary: Healtchecks for Django
Home-page: https://github.com/lincolnloop/django-alive/
Author: Peter Baumgartner
Author-email: pete@lincolnloop.com
License: MIT
Keywords: django,healtcheck,alive
Classifier: Development Status :: 5 - Production/Stable
Classifier: Environment :: Web Environment
Classifier: License :: OSI Approved :: MIT License
Classifier: Operating System :: OS Independent
Classifier: Programming Language :: Python
Classifier: Programming Language :: Python :: 3.6
Classifier: Programming Language :: Python :: 3.7
Classifier: Programming Language :: Python :: 3.8
Classifier: Programming Language :: Python :: 3.9
Classifier: Programming Language :: Python :: 3.10
Classifier: Programming Language :: Python :: 3.11
Classifier: Programming Language :: Python :: 3.12
Classifier: Framework :: Django
License-File: LICENSE
Requires-Dist: django
Provides-Extra: test
Requires-Dist: pytest; extra == "test"
Requires-Dist: pytest-cov; extra == "test"
Requires-Dist: pytest-django; extra == "test"
